updatabot/__init__.py
updatabot/load_url.py
updatabot/logger.py
updatabot/save.py
updatabot/ons/__init__.py
updatabot/ons/load.py
updatabot/ons/schema/ds_root.py
updatabot/ons/schema/ds_version.py
updatabot-0.0.15.dist-info/LICENCE
updatabot-0.0.15.dist-info/METADATA
updatabot-0.0.15.dist-info/WHEEL
updatabot-0.0.15.dist-info/top_level.txt
updatabot-0.0.15.dist-info/RECORD
